nanoarrow/__init__.py
nanoarrow/_array.cpython-310-aarch64-linux-gnu.so
nanoarrow/_array_stream.cpython-310-aarch64-linux-gnu.so
nanoarrow/_buffer.cpython-310-aarch64-linux-gnu.so
nanoarrow/_device.cpython-310-aarch64-linux-gnu.so
nanoarrow/_ipc_lib.cpython-310-aarch64-linux-gnu.so
nanoarrow/_repr_utils.py
nanoarrow/_schema.cpython-310-aarch64-linux-gnu.so
nanoarrow/_static_version.py
nanoarrow/_types.cpython-310-aarch64-linux-gnu.so
nanoarrow/_utils.cpython-310-aarch64-linux-gnu.so
nanoarrow/_version.py
nanoarrow/array.py
nanoarrow/array_stream.py
nanoarrow/c_array.py
nanoarrow/c_array_stream.py
nanoarrow/c_buffer.py
nanoarrow/c_schema.py
nanoarrow/device.py
nanoarrow/extension.py
nanoarrow/extension_canonical.py
nanoarrow/ipc.py
nanoarrow/iterator.py
nanoarrow/schema.py
nanoarrow/visitor.py
nanoarrow-0.7.0.dist-info/METADATA
nanoarrow-0.7.0.dist-info/WHEEL
nanoarrow-0.7.0.dist-info/RECORD
