Metadata-Version: 2.1
Name: nanoarrow
Version: 0.7.0
Summary: Python bindings to the nanoarrow C library
Author-Email: Apache Arrow Developers <dev@arrow.apache.org>
Maintainer-Email: Apache Arrow Developers <dev@arrow.apache.org>
License: Apache-2.0
Project-URL: Homepage, https://arrow.apache.org
Project-URL: Repository, https://github.com/apache/arrow-nanoarrow
Project-URL: Issues, https://github.com/apache/arrow-nanoarrow/issues
Project-URL: Changelog, https://github.com/apache/arrow-nanoarrow/blob/main/CHANGELOG.md
Requires-Python: >=3.9
Provides-Extra: test
Requires-Dist: pyarrow; extra == "test"
Requires-Dist: python-dateutil; extra == "test"
Requires-Dist: pytest; extra == "test"
Requires-Dist: numpy; extra == "test"
Provides-Extra: verify
Requires-Dist: python-dateutil; extra == "verify"
Requires-Dist: pytest; extra == "verify"
Requires-Dist: numpy; extra == "verify"
